abstract_gui/FilesListManager.py
abstract_gui/RightClickManager.py
abstract_gui/SimpleGuiFunctionsManager.py
abstract_gui/__init__.py
abstract_gui/abstract_browser.py
abstract_gui/abstract_gui.py
abstract_gui/abstract_next_read_manager.py
abstract_gui/abstract_window_global_bridge.py
abstract_gui/abstract_window_manager.py
abstract_gui/files_list_manager.py
abstract_gui/main.py
abstract_gui/right_click_test.py
abstract_gui/simple_gui_functions_manager.py
abstract_webgui/FilesListManager.py
abstract_webgui/RightClickManager.py
abstract_webgui/SimpleGuiFunctionsManager.py
abstract_webgui/__init__.py
abstract_webgui/abstract_browser.py
abstract_webgui/abstract_functions.py
abstract_webgui/abstract_gui.py
abstract_webgui/abstract_next_read_manager.py
abstract_webgui/abstract_window_global_bridge.py
abstract_webgui/abstract_window_manager.py
abstract_webgui/files_list_manager.py
abstract_webgui/main.py
abstract_webgui/right_click_test.py
abstract_webgui/simple_gui_functions_manager.py
abstract_webgui-0.1.0.0.dist-info/METADATA
abstract_webgui-0.1.0.0.dist-info/WHEEL
abstract_webgui-0.1.0.0.dist-info/top_level.txt
abstract_webgui-0.1.0.0.dist-info/RECORD
